pymouser/__init__.py
pymouser/mouser.py
pymouser-0.8.dist-info/LICENSE
pymouser-0.8.dist-info/METADATA
pymouser-0.8.dist-info/WHEEL
pymouser-0.8.dist-info/top_level.txt
pymouser-0.8.dist-info/RECORD
