Metadata-Version: 2.1
Name: pymouser
Version: 0.8
Summary: Module to interact with Mouser's Search API
Author-email: Alex Sartori <alex.sartori1997@gmail.com>
Project-URL: Homepage, https://github.com/AlexSartori/pymouser
Classifier: Programming Language :: Python :: 3
Classifier: License :: OSI Approved :: MIT License
Classifier: Operating System :: OS Independent
Requires-Python: >=3.7
License-File: LICENSE
